setup.cfg
setup.py
ecs_explorer/__init__.py
ecs_explorer/ecs_client.py
ecs_explorer/ecs_explorer.py
ecs_explorer/settings.py
ecs_explorer/widgets.py
ecs_explorer.egg-info/PKG-INFO
ecs_explorer.egg-info/SOURCES.txt
ecs_explorer.egg-info/dependency_links.txt
ecs_explorer.egg-info/entry_points.txt
ecs_explorer.egg-info/requires.txt
ecs_explorer.egg-info/top_level.txt