Metadata-Version: 1.1
Name: ecs-explorer
Version: 0.5
Summary: CLI for exploring AWS ECS resources
Home-page: https://github.com/firemanphil/ecs_explorer
Author: Philip Ince
Author-email: fireman.phil@gmail.com
License: UNKNOWN
Download-URL: https://github.com/firemanphil/ecs_explorer/archive/0.5.tar.gz
Keywords: AWS,ECS,urwid,ncurses,cli
Platform: UNKNOWN
